jack_fluidsynth/__init__.py
jack_fluidsynth-1.0.3.dist-info/LICENSE
jack_fluidsynth-1.0.3.dist-info/WHEEL
jack_fluidsynth-1.0.3.dist-info/METADATA
jack_fluidsynth-1.0.3.dist-info/RECORD
